MANIFEST.in
README.md
setup.py
humilis_streams/__init__.py
humilis_streams/meta.yaml.j2
humilis_streams/metadata.py
humilis_streams/outputs.yaml.j2
humilis_streams/resources.yaml.j2
humilis_streams.egg-info/PKG-INFO
humilis_streams.egg-info/SOURCES.txt
humilis_streams.egg-info/dependency_links.txt
humilis_streams.egg-info/entry_points.txt
humilis_streams.egg-info/not-zip-safe
humilis_streams.egg-info/requires.txt
humilis_streams.egg-info/top_level.txt