Metadata-Version: 1.1
Name: humilis-streams
Version: 0.1.0
Summary: Deploys Kinesis streams
Home-page: http://github.com/humilis/humilis-streams
Author: German Gomez-Herrero
Author-email: german@findhotel.net
License: MIT
Platform: UNKNOWN
Classifier: Programming Language :: Python :: 3
